src/__init__.py
src/cursion/__init__.py
src/cursion/api.py
src/cursion/root.py
cursion-0.0.6.dist-info/LICENSE.md
cursion-0.0.6.dist-info/METADATA
cursion-0.0.6.dist-info/WHEEL
cursion-0.0.6.dist-info/entry_points.txt
cursion-0.0.6.dist-info/top_level.txt
cursion-0.0.6.dist-info/RECORD
