Metadata-Version: 2.2
Name: cursion
Version: 0.0.6
Summary: Official Cursion CLI
Author-email: Cursion <hello@cursion.dev>
Project-URL: Homepage, https://github.com/cursion-dev/cli
Project-URL: Issues, https://github.com/cursion-dev/cli/issues
Project-URL: Documentaion, https://docs.cursion.dev
Keywords: regression testing,vrt,visual regression testing
Classifier: Programming Language :: Python :: 3
Classifier: License :: OSI Approved :: MIT License
Classifier: Operating System :: OS Independent
Requires-Python: >=3.9
License-File: LICENSE.md
Requires-Dist: python-dotenv
Requires-Dist: requests
Requires-Dist: rich
Requires-Dist: typer
Dynamic: requires-dist
